TuSanic/__init__.py
TuSanic/tus_file.py
TuSanic/tusanic.py
TuSanic-0.1.0.dev2.dist-info/METADATA
TuSanic-0.1.0.dev2.dist-info/WHEEL
TuSanic-0.1.0.dev2.dist-info/top_level.txt
TuSanic-0.1.0.dev2.dist-info/RECORD
